librapy/__init__.py
librapy/account.py
librapy/common_transactions.py
librapy/lib/__init__.py
librapy/lib/common.py
librapy/lib/hasher.py
librapy/lib/lcs.py
librapy/programs/__init__.py
librapy/programs/create_account.prg
librapy/programs/mint.prg
librapy/programs/peer_to_peer_transfer.prg
librapy/programs/programs.py
librapy/programs/rotate_authentication_key.prg
librapy/proto/__init__.py
librapy/proto/_pb2.py
librapy/proto/access_path_pb2.py
librapy/proto/access_path_pb2_grpc.py
librapy/proto/account_state_blob_pb2.py
librapy/proto/account_state_blob_pb2_grpc.py
librapy/proto/admission_control_pb2.py
librapy/proto/admission_control_pb2_grpc.py
librapy/proto/events_pb2.py
librapy/proto/events_pb2_grpc.py
librapy/proto/get_with_proof_pb2.py
librapy/proto/get_with_proof_pb2_grpc.py
librapy/proto/language_storage_pb2.py
librapy/proto/language_storage_pb2_grpc.py
librapy/proto/ledger_info_pb2.py
librapy/proto/ledger_info_pb2_grpc.py
librapy/proto/mempool_status_pb2.py
librapy/proto/mempool_status_pb2_grpc.py
librapy/proto/proof_pb2.py
librapy/proto/proof_pb2_grpc.py
librapy/proto/transaction_info_pb2.py
librapy/proto/transaction_info_pb2_grpc.py
librapy/proto/transaction_pb2.py
librapy/proto/transaction_pb2_grpc.py
librapy/proto/validator_change_pb2.py
librapy/proto/validator_change_pb2_grpc.py
librapy/proto/validator_public_keys_pb2.py
librapy/proto/validator_public_keys_pb2_grpc.py
librapy/proto/validator_set_pb2.py
librapy/proto/validator_set_pb2_grpc.py
librapy/proto/vm_errors_pb2.py
librapy/proto/vm_errors_pb2_grpc.py
librapy/types/__init__.py
librapy/types/account_address.py
librapy/types/account_resource.py
librapy/types/program.py
librapy/types/resources.py
librapy/types/transactions.py
librapy-0.0.1.dist-info/DESCRIPTION.rst
librapy-0.0.1.dist-info/METADATA
librapy-0.0.1.dist-info/RECORD
librapy-0.0.1.dist-info/WHEEL
librapy-0.0.1.dist-info/metadata.json
librapy-0.0.1.dist-info/top_level.txt
