Metadata-Version: 2.0
Name: librapy
Version: 0.0.1
Summary: A Libra client library
Home-page: https://github.com/davidiw/librapy
Author: David Wolinsky
Author-email: isaac.wolinsky@gmail.com
License: MIT
Platform: UNKNOWN
Classifier: Programming Language :: Python :: 3
Classifier: License :: OSI Approved :: MIT License
Classifier: Operating System :: OS Independent
Requires-Python: >=3.6
Requires-Dist: PyNaCl (==1.3.0)
Requires-Dist: grpcio (==1.23.0)
Requires-Dist: grpcio-tools (==1.23.0)
Requires-Dist: protobuf (==3.9.1)
